amazonpy/__init__.py
amazonpy/amazon.py
amazonpy/proxies.py
amazonpy/scrap.py
amazonpy-2.0.0.dist-info/LICENSE
amazonpy-2.0.0.dist-info/METADATA
amazonpy-2.0.0.dist-info/WHEEL
amazonpy-2.0.0.dist-info/top_level.txt
amazonpy-2.0.0.dist-info/RECORD
