Metadata-Version: 2.1
Name: amazonpy
Version: 2.0.0
Summary: amazon scraping library.
Home-page: https://github.com/nanato12/amazonpy
Author: nanato12
Author-email: admin@nanato12.info
License: MIT
Keywords: amazon amazonpy amazon_scraping
Platform: UNKNOWN
Classifier: License :: OSI Approved :: MIT License
Classifier: Programming Language :: Python :: 3.6
Classifier: Programming Language :: Python :: 3.7
Classifier: Programming Language :: Python :: 3.8
Classifier: Programming Language :: Python :: 3.9
Classifier: Programming Language :: Python :: 3 :: Only
Requires-Dist: bs4
Requires-Dist: fake-useragent
Requires-Dist: requests
